Metadata-Version: 2.1
Name: django-graphene-permissions
Version: 0.0.4
Summary: DRF like permission system for django graphene
Home-page: https://github.com/taoufik07/django-graphene-permissions
Author: Taoufik Abbassid
Author-email: abacidtaoufik@gmail.com
License: BSD
Platform: UNKNOWN
Classifier: License :: OSI Approved :: BSD License
Classifier: Programming Language :: Python
Classifier: Programming Language :: Python :: 3
Classifier: Framework :: Django
Classifier: Operating System :: OS Independent
